uiautomator2/__init__.py
uiautomator2/__main__.py
uiautomator2/_input.py
uiautomator2/_proto.py
uiautomator2/_selector.py
uiautomator2/abcd.py
uiautomator2/abstract.py
uiautomator2/base.py
uiautomator2/core.py
uiautomator2/exceptions.py
uiautomator2/image.py
uiautomator2/init.py
uiautomator2/messagebox.py
uiautomator2/screenrecord.py
uiautomator2/settings.py
uiautomator2/swipe.py
uiautomator2/utils.py
uiautomator2/version.py
uiautomator2/watcher.py
uiautomator2/webview.py
uiautomator2/widget.py
uiautomator2/xpath.py
uiautomator2/assets/ADBKeyboard.apk
uiautomator2/assets/apk_version.txt
uiautomator2/assets/app-uiautomator-test.apk
uiautomator2/assets/app-uiautomator.apk
uiautomator2/assets/sync.sh
uiautomator2/ext/__init__.py
uiautomator2/ext/htmlreport/__init__.py
uiautomator2/ext/info/__init__.py
uiautomator2/ext/info/conf.py
uiautomator2/ext/perf/__init__.py
uiautomator2/ext/xpath/__init__.py
uiautomator2_henry-2.16.31.dist-info/licenses/LICENSE
uiautomator2_henry-2.16.31.dist-info/METADATA
uiautomator2_henry-2.16.31.dist-info/WHEEL
uiautomator2_henry-2.16.31.dist-info/entry_points.txt
uiautomator2_henry-2.16.31.dist-info/top_level.txt
uiautomator2_henry-2.16.31.dist-info/RECORD
